pysumtypes/__init__.py
PySumTypes-0.0.1.dist-info/LICENSE
PySumTypes-0.0.1.dist-info/METADATA
PySumTypes-0.0.1.dist-info/WHEEL
PySumTypes-0.0.1.dist-info/top_level.txt
PySumTypes-0.0.1.dist-info/RECORD
