Metadata-Version: 2.1
Name: PySumTypes
Version: 0.0.1
Summary: Sum Types for Python
Home-page: https://github.com/danpozmanter/PySumTypes
Author: Dan Pozmanter
License: BSD
Keywords: sumtypes adt discriminatedunions uniontypes algebraicdatatypes
Platform: UNKNOWN
Classifier: Intended Audience :: Developers
Classifier: License :: OSI Approved :: BSD License
Classifier: Operating System :: OS Independent
Classifier: Programming Language :: Python :: 3
Classifier: Topic :: Software Development :: Libraries :: Python Modules
Requires-Python: >=3.7
